SearchForThis
